tensorci_client/__init__.py
tensorci_client/api.py
tensorci_client/definitions.py
tensorci_client/exps.py
tensorci_client/pyredis.py
tensorci_client/tensorci.py
tensorci_client/graphs/__init__.py
tensorci_client/graphs/data_series.py
tensorci_client/graphs/xy_scatter_plot.py
tensorci_client/utils/__init__.py
tensorci_client/utils/envs.py
tensorci_client/utils/slug.py
tensorci_client/utils/socket.py
tensorci_client-0.0.14.dist-info/DESCRIPTION.rst
tensorci_client-0.0.14.dist-info/METADATA
tensorci_client-0.0.14.dist-info/RECORD
tensorci_client-0.0.14.dist-info/WHEEL
tensorci_client-0.0.14.dist-info/metadata.json
tensorci_client-0.0.14.dist-info/top_level.txt
