Metadata-Version: 2.0
Name: tensorci-client
Version: 0.0.14
Summary: TensorCI API Client
Home-page: https://github.com/tensorci/tensorci-client
Author: Ben Whittle
Author-email: benwhittle31@gmail.com
License: MIT
Platform: UNKNOWN
Requires-Dist: requests (==2.18.4)
Requires-Dist: awesome-slugify (==1.6.5)
Requires-Dist: redis (==2.10.6)
Requires-Dist: websocket-client (==0.47.0)
